{
	"_meta": {
		"sources": [
			{
				"json": "MM-ES",
				"abbreviation": "MM-ES",
				"full": "Monster Manual - Español",
				"color": "27c602",
				"authors": [
					"Garrim"
				],
				"convertedBy": [
					""
				],
				"version": "2021.8.18",
				"url": ""
			}
		],
		"dateAdded": 1412035200,
		"dateLastModified": 1629284141
	},
	"monster": [
		{
            "name": "Osgo",
            "source": "MM-ES",
            "page": 33,
            "srd": true,
            "otherSources": [{
                    "source": "LMoP-ES"
                }
            ],
            "size": "M",
            "type": {
                "type": "humanoid",
                "tags": ["trasgo"]
            },
            "alignment": ["C", "E"],
            "ac": [{
                    "ac": 16,
                    "from": ["{@item armadura de pieles|PHB-ES}", "{@item escudo|PHB-ES}"]
                }
            ],
            "hp": {
                "average": 27,
                "formula": "5d8 + 5"
            },
            "speed": {
                "walk": 30
            },
            "str": 15,
            "dex": 14,
            "con": 13,
            "int": 8,
            "wis": 11,
            "cha": 9,
            "skill": {
                "stealth": "+6",
                "survival": "+2"
            },
            "senses": ["darkvision 60 ft."],
            "passive": 10,
            "languages": ["Común", "Goblin"],
            "cr": "1",
            "trait": [{
                    "name": "Bruto",
                    "entries": ["Cuando el osgo impacta con un ataque realizado con un arma cuerpo a cupero, tira una vez más el daño del arma y añádelo al resultado (ya incluido)."]
                }, {
                    "name": "Ataque por Sorpresa",
                    "entries": ["Si el osgo sorprende a una criatura y la impacta con un ataque durante el primer asalto del combate, este causa 7 ({@dice 2d6}) de daño adicional."]
                }
            ],
            "action": [{
                    "name": "Lucero del alba",
                    "entries": ["{@atk mw} {@hit 4} to hit, reach 5 ft., one target. {@h}11 ({@damage 2d8 + 2}) piercing damage."]
                }, {
                    "name": "Jabalina",
                    "entries": ["{@atk mw,rw} {@hit 4} to hit, reach 5 ft. or range 30/120 ft., one target. {@h}9 ({@damage 2d6 + 2}) piercing damage in melee or 5 ({@damage 1d6 + 2}) piercing damage at range."]
                }
            ],
            "environment": ["underdark", "praderas", "bosques"],
            "tokenUrl": "https://5e.tools/img/MM/Bugbear.png",
            "soundClip": {
                "type": "internal",
                "path": "bestiary/bugbear.mp3"
            },
            "traitTags": ["Brute"],
            "senseTags": ["D"],
            "languageTags": ["C", "GO"],
            "damageTags": ["P"],
            "miscTags": ["MW", "RW", "THW"],
			"fluff": {
				"entries": [
					{
						"type": "entries",
						"entries": [{
								"type": "entries",
								"entries": ["Los osgos nacieron para combatir y provocar el caos. Estas criaturas basan su supervivencia en la caza y las incursiones. Abusan de los débiles y desprecian a quien intenta darles órdenes, pero su amor por la matanza les lleva a luchar bajo las órdenes de alguien poderoso si el derramamiento de sangre y el tesoro están asegurados", {
										"name": "Trasgos",
										"type": "entries",
										"entries": ["A los osgos se les ve frecuentemente en compañía de sus primos, los hobgoblins y los goblins. Esclavizan normalmente a los goblins a los que se encuentran y obligan a los hobgoblins a entregarles oro y comida a cambio de servirles como exploradores y tropas de choque. Uno no debe fiarse nunca de los osgos, incluso tras haberles pagado. Sin embargo, los goblins y los hobgoblins entienden que, al margen de lo mucho que drenen los recursos de sus tribus, estas criaturas poseen una fuerza considerable."]
									}, {
										"name": "Seguidores de Hruggek",
										"type": "entries",
										"entries": ["Los osgos adoran a Hruggek, un dios menor que habita en el plano de Aqueronte. Cuando no están cerca de sus parientes trasgos, los osgos forman bandas poco disciplinadas, guiados por su miembro más feroz. Estas criaturas creen que cuando mueren, sus espíritus tienen la oportunidad de luchar al lado de Hruggek. Para considerarse dignos de tal honor, tratan de derrotar a la mayor cantidad de enemigos posible."]
									}, {
										"name": "Emboscadores mercenarios",
										"type": "entries",
										"entries": ["A pesar de su aspecto amenazador, los osgos son sorprendentemente sigilosos. Les encanta tender emboscadas y huir si se sienten sobrepasados. Son mercenarios fiables siempre que se les suministre alimento, bebida y tesoro, pero un osgo olvidará cualquier vínculo si su vida está en peligro. Es común dejar a un miembro herido de una banda de osgos atrás si eso ayuda al resto del grupo a escapar. Posteriormente, ese osgo abandonado podría ayudar a sus enemigos a localizar a sus antiguos compañeros si así puede salvar su vida. "]
									}
								]
							}
						]
					}
				],
				"images": [{
						"type": "image",
						"href": {
							"type": "internal",
							"path": "bestiary/MM/Bugbear.jpg"
						}
					}
				]
			}
        },
		{
            "name": "Plebeyo",
            "source": "MM-ES",
            "page": 345,
            "srd": true,
            "otherSources": [
                {
                    "source": "LMoP-ES"
                }
            ],
            "size": "M",
            "type": {
                "type": "humanoid",
                "tags": ["cualquier raza"]
            },
            "alignment": ["A"],
            "ac": [10],
            "hp": {
                "average": 4,
                "formula": "1d8"
            },
            "speed": {
                "walk": 30
            },
            "str": 10,
            "dex": 10,
            "con": 10,
            "int": 10,
            "wis": 10,
            "cha": 10,
            "passive": 10,
            "languages": ["uno cualquiera (normalmente común)"],
            "cr": "0",
            "action": [{
                    "name": "Garrote",
                    "entries": ["{@atk mw} {@hit 2} to hit, reach 5 ft., one target. {@h}2 ({@damage 1d4}) bludgeoning damage."]
                }
            ],
            "environment": ["zonas polares", "desiertos", "costas", "praderas", "colinas", "ciudades", "bosques"],
            "tokenUrl": "https://5e.tools/img/MM/Commoner.png",
            "soundClip": {
                "type": "internal",
                "path": "bestiary/commoner.mp3"
            },
            "languageTags": ["C", "X"],
            "damageTags": ["B"],
            "miscTags": ["MW"],
            "fluff": 
			{
				"entries": [
					{
						"type": "entries",
						"entries": [
							{
								"type": "entries",
								"entries": ["Campesinos, sirvientes, esclavos, siervos, peregrinos, mercaderes, artesanos y ermitaños son todos ellos ejemplos de plebeyos."]
							}
						]
					}
				]
			}
        },
		{
            "name": "Sectario",
            "source": "MM-ES",
            "page": 345,
            "srd": true,
            "otherSources": [
                {
                    "source": "LMoP-ES"
                }
            ],
            "size": "M",
            "type": {
                "type": "humanoid",
                "tags": ["cualquier raza"]
            },
            "alignment": ["L", "NX", "C", "NY", "E"],
            "ac": [{
                    "ac": 12,
                    "from": ["{@item armadura de cuero|PHB-ES}"]
                }
            ],
            "hp": {
                "average": 9,
                "formula": "2d8"
            },
            "speed": {
                "walk": 30
            },
            "str": 11,
            "dex": 12,
            "con": 10,
            "int": 10,
            "wis": 11,
            "cha": 10,
            "skill": {
                "deception": "+2",
                "religion": "+2"
            },
            "passive": 10,
            "languages": ["uno cualquiera (normalmente común)"],
            "cr": "1/8",
            "trait": [{
                    "name": "Devoción Oscura",
                    "entries": ["El sectario tiene ventaja en las tiradas de salvación para evitar ser {@condition hechizado|PHB-ES} o {@condition asustado|PHB-ES}."]
                }
            ],
            "action": [{
                    "name": "Cimitarra",
                    "entries": ["{@atk mw} {@hit 3} to hit, reach 5 ft., one creature. {@h}4 ({@damage 1d6 + 1}) slashing damage."]
                }
            ],
            "tokenUrl": "https://5e.tools/img/MM/Cultist.png",
            "soundClip": {
                "type": "internal",
                "path": "bestiary/cultist.mp3"
            },
            "languageTags": ["C", "X"],
            "damageTags": ["S"],
            "miscTags": ["MW"],
            "fluff": {
				"entries": [
					{
						"type": "entries",
						"entries": [{
								"type": "entries",
								"entries": ["Los sectarios juran lealtad a poderes oscuros: príncipes elementales, señores demoníacos o archidiablos. La mayoría de ellos ocultan sus actividades para evitar ser condenados al ostracismo, apresados o ejecutados por sus creencias. A diferencia de los acólitos malvados, los sectarios suelen mostrar señales evidentes de locura en sus actos y creencias."]
							}
						]
					}
				],
				"images": [{
						"type": "image",
						"href": {
							"type": "internal",
							"path": "bestiary/MM/Cultist.png"
						}
					}
				]
			}
        },
		{
            "name": "Doppelganger",
            "source": "MM-ES",
            "page": 82,
            "srd": true,
            "otherSources": [
                {
                    "source": "LMoP"
                }
            ],
            "size": "M",
            "type": {
                "type": "monstrosity",
                "tags": ["cambiaformas"]
            },
            "alignment": ["N"],
            "ac": [14],
            "hp": {
                "average": 52,
                "formula": "8d8 + 16"
            },
            "speed": {
                "walk": 30
            },
            "str": 11,
            "dex": 18,
            "con": 14,
            "int": 11,
            "wis": 12,
            "cha": 14,
            "skill": {
                "deception": "+6",
                "insight": "+3"
            },
            "senses": ["darkvision 60 ft."],
            "passive": 11,
            "conditionImmune": ["charmed"],
            "languages": ["Común"],
            "cr": "3",
            "trait": [{
                    "name": "Cambiaformas",
                    "entries": ["El doppelganger puede usar su acción para polimorfarse en un humanoide Mediano o Pequeño que haya visto antes, o volver a asumir su auténtica forma. Su perfil, con la excepción del tamaño, es el mismo en todas las formas. Cualquier elemento de equipo que lleve o vista no se transformará. Si muere, volverá a su forma auténtica. "]
                }, {
                    "name": "Emboscador",
                    "entries": ["Durante el primer asalto de un combate, el doppelganger tiene ventaja en las tiradas de ataque contra cualquier criatura a la que haya sorprendido."]
                }, {
                    "name": "Ataque por sorpresa",
                    "entries": ["Si el doppelganger sorprende a una criatura y la impacta con un ataque durante el primer asalto del combate, ese ataque causa 10 ({@dice 3d6}) de daño adicionales."]
                }
            ],
            "action": [{
                    "name": "Ataque múltiple",
                    "entries": ["El doppelganger realiza dos ataques cuerpo a cuerpo."]
                }, {
                    "name": "Golpe",
                    "entries": ["{@atk mw} {@hit 6} to hit, reach 5 ft., one target. {@h}7 ({@damage 1d6 + 4}) bludgeoning damage."]
                }, {
                    "name": "Leer pensamientos",
                    "entries": [
						"El doppelganger puede leer mediante la magia los pensamientos superficiales de una criatura que se encuentre a 60 pies o menos. Este efecto es capaz de atravesar la mayoría de las barreras, pero se ve bloqueado por 3 pies de madera o tierra, 2 pies de piedra, 2 pulgadas de metal, o una fina lámina de plomo. Si el objetivo permanece dentro del alcance y el doppelganger mantiene la concentración (como si se concentrara en un conjuro), este podrá seguir percibiendo sus pensamientos. Mientras le esté leyendo la mente, el doppelganger tendrá ventaja en las pruebas de Sabiduría ({@skill Insight|Perspicacia}) y Carisma ({@skill Deception|Engaño}, {@skill Intimidation|Intimidación} y {@skill Persuasion|Persuasión}) contra el objetivo."
					]
                }
            ],
            "environment": ["underdark", "ciudades"],
            "tokenUrl": "https://5e.tools/img/MM/Doppelganger.png",
            "soundClip": {
                "type": "internal",
                "path": "bestiary/doppelganger.mp3"
            },
            "traitTags": ["Ambusher", "Shapechanger"],
            "senseTags": ["D"],
            "actionTags": ["Multiattack"],
            "languageTags": ["C"],
            "damageTags": ["B"],
            "miscTags": ["MW"],
            "fluff": {
				"entries": [
					{
						"type": "entries",
						"entries": [{
								"type": "entries",
								"entries": [
									"Los doppelgangers son cambiaformas insidiosos que toman el aspecto de otros humanoides, persiguiendo o atrayendo a sus víctimas hacia su perdición mediante el engaño y la distracción. Pocas criaturas son capaces de causar tanto miedo, sospecha y engaño como un doppelganger. Se conocen casos en todos los lugares y en todas las culturas, ya que son capaces de disfrazarse de cualquier individuo de cualquier raza.", 
									{
										"name": "Robando secretos",
										"type": "entries",
										"entries": ["La capacidad de adquirir cualquier forma de un doppelganger les permite mezclarse en cualquier comunidad o grupo, pero su transformación no les hace conocer la lengua, las costumbres, los recuerdos o la personalidad. En muchas ocasiones, estas criaturas siguen o capturan a aquellos que quieren suplantar, estudiándolos y sondeando su mente para conocer sus secretos. Pueden leer los pensamientos superficiales de un objetivo, lo que les permite averiguar el nombre, los deseos, los miedos, así como algunos recuerdos aislados. Los doppelgangers que planean suplantar a una criatura durante un largo período de tiempo podrían dejar a su doble vivo y en algún lugar cercano durante semanas, sondeando su mente diariamente para descubrir cómo se comporta y cómo habla de verdad."]
									}, {
										"name": "Estafadores hedonistas",
										"type": "entries",
										"entries": ["Los doppelgangers trabajan solos o en grupos pequeños, cambiando el papel de una estafa a otra. Mientras que uno podría tomar el lugar de un mercader o noble asesinado, los demás asumen las identidades que hagan falta, interpretando a la familia o los sirvientes, lo que les permite vivir de las riquezas de la víctima."]
									}, {
										"name": "Cambiantes",
										"type": "entries",
										"entries": ["Estas criaturas son demasiado indolentes y carecen del interés necesario para criar a su progenie. Los varones asumen la forma de atractivos miembros masculinos de una especie y seducen a las hembras, a las que luego dejan solas para que críen a su progenie. Una cría de doppelganger parece un miembro normal de la especie de la madre hasta que llega la adolescencia, momento en el que descubre su naturaleza real y busca a los de su especie para unirse a ellos."]
									}
								]
							}
						]
					}
				],
				"images": [{
						"type": "image",
						"href": {
							"type": "internal",
							"path": "bestiary/MM/Doppelganger.jpg"
						}
					}
				]
			}
        }
	]
}
